Metadata-Version: 2.1
Name: bascontrolns
Version: 0.0.3
Summary: BASpi/20/pi/ao/po control module API interface
Home-page: https://github.com/sjpbailey/bascontrol_ns
Author: Steven Bailey and Gerrod Bailey
Author-email: sjpbailey@comcast.net
License: UNKNOWN
Platform: UNKNOWN
Classifier: Development Status :: 5 - Production/Stable
Classifier: Programming Language :: Python :: 3.7
Classifier: License :: OSI Approved :: MIT License
Classifier: Operating System :: OS Independent
